stdlib_utils/__init__.py
stdlib_utils/checksum.py
stdlib_utils/constants.py
stdlib_utils/exceptions.py
stdlib_utils/loggers.py
stdlib_utils/misc.py
stdlib_utils/multiprocessing_utils.py
stdlib_utils/parallelism_framework.py
stdlib_utils/parallelism_utils.py
stdlib_utils/ports.py
stdlib_utils/queue_utils.py
stdlib_utils/threading_utils.py
stdlib_utils/xml.py
stdlib_utils-0.5.2.dist-info/LICENSE
stdlib_utils-0.5.2.dist-info/METADATA
stdlib_utils-0.5.2.dist-info/WHEEL
stdlib_utils-0.5.2.dist-info/top_level.txt
stdlib_utils-0.5.2.dist-info/RECORD
